fio/__init__.py
fio/fio.py
fio/schema.py
fio/cls/__init__.py
fio/cls/base.py
fio/cls/decode.py
fio/cls/encode.py
fio/cls/recon.py
fio/utils/__init__.py
fio/utils/decode.py
fio/utils/encode.py
fio/utils/features.py
fio/utils/types.py
fio/utils/utils.py
fio-0.0.6.dist-info/METADATA
fio-0.0.6.dist-info/RECORD
fio-0.0.6.dist-info/WHEEL
fio-0.0.6.dist-info/top_level.txt
