Metadata-Version: 2.1
Name: fio
Version: 0.0.6
Summary: Feature I/O for TensorFlow
Home-page: https://gitlab.com/SumNeuron/fio
Author: Sumner Magruder
Author-email: sumner.magruder@zmnh.uni-hamburg.de
License: UNKNOWN
Platform: UNKNOWN
Classifier: Programming Language :: Python :: 3.6
Classifier: License :: OSI Approved :: MIT License
Classifier: Operating System :: OS Independent
